adblockeval/__init__.py
adblockeval/ahocorasick.py
adblockeval/rules.py
adblockeval-0.3.dist-info/LICENSE
adblockeval-0.3.dist-info/METADATA
adblockeval-0.3.dist-info/WHEEL
adblockeval-0.3.dist-info/top_level.txt
adblockeval-0.3.dist-info/RECORD
