Metadata-Version: 2.1
Name: adblockeval
Version: 0.3
Summary: Evaluates URLs against AdBlock rules efficiently to check which rules would block them, if any.
Home-page: https://github.com/hprid/adblockeval
Author: Henning Pridöhl
Author-email: henning.pridoehl@hprid.de
License: MIT
Keywords: adblock
Platform: any
Classifier: Development Status :: 4 - Beta
Classifier: License :: OSI Approved :: MIT License
Classifier: Programming Language :: Python :: 3
Classifier: Programming Language :: Python :: 3.5
Classifier: Programming Language :: Python :: 3.6
Classifier: Programming Language :: Python :: 3.7
Requires-Python: >= 3.5
